prize/__init__.py
prize/aa.txt.py
prize/main.py
prize/pip_trigger.py
prize/setting.py
prize/test.py
prize/ui/__init__.py
prize/ui/app.py
prize/ui/menu_setting.py
prize/util/__init__.py
prize/util/number.py
prize/util/ui_placer.py
tests/__init__.py
tests/test_main.py
tests/test_number.py
choujiang-1.0.3.dist-info/LICENSE
choujiang-1.0.3.dist-info/METADATA
choujiang-1.0.3.dist-info/WHEEL
choujiang-1.0.3.dist-info/entry_points.txt
choujiang-1.0.3.dist-info/top_level.txt
choujiang-1.0.3.dist-info/RECORD
