Metadata-Version: 2.1
Name: choujiang
Version: 1.0.3
Summary: A tool to pickup winner randomly from inputs
Home-page: https://blog.csdn.net/geeklevin
Author: levin
Author-email: levinmhliu@gmail.com
License: Apache License 2.0
Keywords: prize,choujiang,levin,leixuewei
Platform: all
Classifier: Intended Audience :: Developers
Classifier: Operating System :: OS Independent
Classifier: Natural Language :: Chinese (Simplified)
Classifier: Programming Language :: Python
Classifier: Programming Language :: Python :: 2
Classifier: Programming Language :: Python :: 2.7
Classifier: Programming Language :: Python :: 3
Classifier: Programming Language :: Python :: 3.5
Classifier: Programming Language :: Python :: 3.6
Classifier: Programming Language :: Python :: 3.7
Classifier: Programming Language :: Python :: 3.8
Classifier: Programming Language :: Python :: 3.9
Classifier: Topic :: Software Development :: Libraries
License-File: LICENSE
Requires-Dist: renxianqi
